README.md
pyproject.toml
setup.cfg
setup.py
whoishome/__init__.py
whoishome/whoishome
whoishome.egg-info/PKG-INFO
whoishome.egg-info/SOURCES.txt
whoishome.egg-info/dependency_links.txt
whoishome.egg-info/requires.txt
whoishome.egg-info/top_level.txt