Metadata-Version: 2.1
Name: whoishome
Version: 0.0.9
Summary: A simple python CLI dashboard which uses nmap to help you keep track of who's on your network (made beautiful with the python library 'rich').
Home-page: https://github.com/jackeown/whoishome
License: UNKNOWN
Platform: UNKNOWN
